easysqulite_321onoff/__init__.py
easysqulite_321onoff/easysqulite.py
easysqulite_321onoff-0.0.1.dist-info/METADATA
easysqulite_321onoff-0.0.1.dist-info/WHEEL
easysqulite_321onoff-0.0.1.dist-info/entry_points.txt
easysqulite_321onoff-0.0.1.dist-info/license_files/LICENSE
easysqulite_321onoff-0.0.1.dist-info/RECORD
