Metadata-Version: 2.1
Name: easysqulite-321onoff
Version: 0.0.1
Summary: Easy Squlit3 For Beginners
Project-URL: Bug Tracker, https://github.com/git4o/easysqulite/issues
Project-URL: Homepage, https://github.com/git4o/easysqulite
Author-email: Orion <help@mylittleyoutubetest.com>
License: Copyright (c) 2022 The Python Packaging Authority
Classifier: License :: OSI Approved :: MIT License
Classifier: Operating System :: OS Independent
Classifier: Programming Language :: Python :: 3
Requires-Python: >=3.7
